{
  "version": "1.0.0",
  "created_at": "2025-10-10T13:39:03.695029",
  "seeding_operations": {
    "reference_data": {
      "seed_name": "reference_data",
      "seed_version": "1.0.0",
      "status": "completed",
      "started_at": "2025-10-21T13:03:43.447978",
      "completed_at": "2025-10-21T13:03:49.872213",
      "environment": "docker",
      "forced": true,
      "records_created": 13673,
      "records_updated": 0,
      "execution_time": 6.437460660934448,
      "error_message": ""
    },
    "test_users": {
      "seed_name": "test_users",
      "seed_version": "1.0.0",
      "status": "completed",
      "started_at": "2025-10-21T13:03:49.881802",
      "completed_at": "2025-10-21T13:03:51.354072",
      "environment": "docker",
      "forced": true,
      "records_created": 0,
      "records_updated": 0,
      "execution_time": 1.4150753021240234,
      "error_message": ""
    },
    "car_generations": {
      "seed_name": "car_generations",
      "seed_version": "1.0.0",
      "status": "completed",
      "started_at": "2025-10-21T13:03:51.423336",
      "completed_at": "2025-10-21T13:03:51.590675",
      "environment": "docker",
      "forced": true,
      "records_created": 131,
      "records_updated": 0,
      "execution_time": 0.13900470733642578,
      "error_message": ""
    },
    "formatted_addresses": {
      "seed_name": "formatted_addresses",
      "seed_version": "1.0.0",
      "status": "completed",
      "started_at": "2025-10-21T13:03:51.639768",
      "completed_at": "2025-10-21T13:03:51.737406",
      "environment": "docker",
      "forced": true,
      "records_created": 0,
      "records_updated": 0,
      "execution_time": 0.1087346076965332,
      "error_message": ""
    },
    "car_ads": {
      "seed_name": "car_ads",
      "seed_version": "1.0.0",
      "status": "completed",
      "started_at": "2025-10-21T13:03:51.759140",
      "completed_at": "2025-10-21T13:03:51.858925",
      "environment": "docker",
      "forced": true,
      "records_created": 0,
      "records_updated": 0,
      "execution_time": 0.10300970077514648,
      "error_message": ""
    },
    "car_images": {
      "seed_name": "car_images",
      "seed_version": "1.0.0",
      "status": "completed",
      "started_at": "2025-10-21T13:03:51.868923",
      "completed_at": "2025-10-21T13:03:51.901266",
      "environment": "docker",
      "forced": true,
      "records_created": 0,
      "records_updated": 0,
      "execution_time": 0.031110525131225586,
      "error_message": ""
    }
  }
}